{
    "content": "<p>&nbsp;</p>\n\n<p><br />\n0、<br />\n1、<br />\n2、<br />\n3、<br />\n4、<br />\n[static data]<br />\n500 100 -300 200 -300<br />\n[/static data]</p>\n\n<p>0、<br />\n1、<br />\n2、冥炎劍1打攻擊力 : 312%%<br />\n3、冥炎劍第2擊攻擊力 : 468%%<br />\n4、冥炎劍第3擊攻擊力 : 936%%<br />\n5、冥炎攻擊次數 : 8次<br />\n6、冥炎攻擊間隔 : 0.5秒<br />\n7、冥炎攻擊力 : 独立攻击力 x 0.31<br />\n8、<br />\n9、<br />\n10、<br />\n11、<br />\n12、<br />\n[level info]<br />\n13 30000 312 312 468 936 8 500 31 90 90 90 90 90</p>",
    "auth_users": "学院搬运工",
    "img": "https://dafstatic.oss-cn-beijing.aliyuncs.com/static/title/level4.gif",
    "create_at": "2023-05-07T20:18:41.606",
    "view_num": 28
}