{
    "content": "<p>参考资源：</p>\n\n<p>https://www.123pan.com/s/tJCtVv-GV6EH.html提取码:p9cA</p>\n\n<p>任务说明</p>\n\n<pre>\n<code>列表：\n代码\t`common/requiem/文件名.qst`\n\n自己编代码和文件名\n\n任务类型代码：\n\n每日任务：\n[grade]\n\t`[daily]`\n\n重复任务：\n[grade]\n\t`[normaly repeat]`\n\n普通任务：\n[grade]\n\t`[common unique]`\n\n成就任务：\n[grade]\n\t`[achievement]`\n\n奖励QP点，这个代码放接任务等级代码的下面\n只能加到普通或者重复任务上\n[quest point]\n\t8888\t</code></pre>\n\n<p>&nbsp;</p>",
    "auth_users": "玲珑",
    "img": "https://dafstatic.oss-cn-beijing.aliyuncs.com/static/title/level6.gif",
    "create_at": "2024-04-21T13:27:36.040",
    "view_num": 731
}