{
    "content": "<p>by:bennimu6<br />\nhttp://tieba.baidu.com/p/4129833509<br />\n&nbsp;<img alt=\"\" height=\"599\" src=\"/media/uploads/2023/05/07/image-20230507213712-1.png\" width=\"1130\" /><br />\n&nbsp;<img alt=\"\" height=\"606\" src=\"/media/uploads/2023/05/07/image-20230507213722-2.png\" width=\"1131\" /><br />\n&nbsp;<br />\n&nbsp;<br />\n&nbsp;<br />\n加百利出现的文件在这个里面<br />\n&nbsp;<img alt=\"\" height=\"25\" src=\"/media/uploads/2023/05/07/image-20230507213730-3.png\" width=\"126\" /><br />\n打开后是这样的<br />\n&nbsp;<img alt=\"\" height=\"355\" src=\"/media/uploads/2023/05/07/image-20230507213735-4.png\" width=\"328\" /><br />\n&nbsp;<br />\n前面2行我不知道是什么~~<br />\ndungeon /dungeon 这段是加百利在特殊地图出现的概率（就是远古地图什么的他会卖远古地图的材料）<br />\n41 应该是地下城的代码，1000是德拉利 就是那个老太太！5个一万就是出现几率~！！<br />\nlevel section 中 0 1 18 是代表 0 是表示 1-18级地下城。1是表示 19-27级地下城。<br />\n重点在level npc 第一段0 1000 10000 10000 10000 10000 10000 这里0表示1-18级地下城中出现德拉利的概率，10000是 必出！<br />\n后面是0 1002 0 0 0 0 0 这个1002就是加卖装备小加商店代码 这里1-18级地下城是不会出现加百利的<br />\n后面是0 1003 0 0 0 0 0 这个1003是卖材料的小加商店代码 同样不会出现！ 再后面的应该知道什么意思！<br />\nNPC<br />\nlevel 中是1002加百利卖的东西， 下面还有1003加百利卖的东西 具体卖什么东西的几率我还没看懂！！<br />\n&nbsp;<br />\n这里 1000 1002 1003 3个npc 出现概率加起来是10000！ 但是我改成别的数加起来10000 ./run 会出错！！！<br />\n我是把德拉利出现的几率直接替换到1002后面，我觉得1003的小加 出现没用就是卖点材料！ 这样1002加百利就出现的和德拉利一样勤快了！ 具体几率希望有人帮忙看下，怎么改才不会出错！！！！<br />\n&nbsp;<br />\n补充一下还有个1004加百利 就是远古加百利，卖远古设计图的!!!<br />\n&nbsp;<img alt=\"\" height=\"29\" src=\"/media/uploads/2023/05/07/image-20230507213742-5.png\" width=\"597\" /><br />\n这个是19-27级地下城出现加百利的几率， 这里我已经改过了！ 但是我改成1 1000 2000 2000 2000 2000 2000 1 1002 7000 7000 7000 7000 7000 1 1003 1000 1000 1000 1000 1000 ./run 的时候好像会出错~~~<br />\n求教为什么啊~~！！</p>\n\n<p>&nbsp;</p>\n\n<p>&nbsp;</p>",
    "auth_users": "学院搬运工",
    "img": "https://dafstatic.oss-cn-beijing.aliyuncs.com/static/title/level4.gif",
    "create_at": "2023-05-07T21:37:44.421",
    "view_num": 655
}