{
    "content": "<p><span style=\"color:#0000ff; font-family:微软雅黑; font-size:small\">[field image]</span></p>\n\n<p><span style=\"color:#0000ff; font-family:微软雅黑; font-size:small\">`Item/FieldImage.img` 32 </span></p>\n\n<p>&nbsp;</p>\n\n<p><span style=\"color:#0000ff; font-family:微软雅黑; font-size:small\">地图上显示图标贴图</span></p>\n\n<p><span style=\"color:#0000ff; font-family:微软雅黑; font-size:small\">[stackable type]</span></p>\n\n<p><span style=\"color:#0000ff; font-family:微软雅黑; font-size:small\">`[waste]` 0 </span></p>\n\n<p><span style=\"color:#0000ff; font-family:微软雅黑; font-size:small\">[expert type]</span></p>\n\n<p><span style=\"color:#0000ff; font-family:微软雅黑; font-size:small\">`[doll_controller]`</span></p>\n\n<p>&nbsp;</p>\n\n<p><span style=\"color:#0000ff; font-family:微软雅黑; font-size:small\">道具类型：消耗类 </span></p>\n\n<p><span style=\"color:#0000ff; font-family:微软雅黑; font-size:small\">职业类型：人偶师</span></p>\n\n<p><span style=\"color:#0000ff; font-family:微软雅黑; font-size:small\">[sub type]</span></p>\n\n<p><span style=\"color:#0000ff; font-family:微软雅黑; font-size:small\">2 </span></p>\n\n<p>&nbsp;</p>\n\n<p><span style=\"color:#0000ff; font-family:微软雅黑; font-size:small\">子类型：2 （未知）</span></p>\n\n<p><span style=\"color:#0000ff; font-family:微软雅黑; font-size:small\">[cooltime group]</span></p>\n\n<p><span style=\"color:#0000ff; font-family:微软雅黑; font-size:small\">100 </span></p>\n\n<p>&nbsp;</p>\n\n<p><span style=\"color:#0000ff; font-family:微软雅黑; font-size:small\">冷却时间组：100</span></p>\n\n<p><span style=\"color:#0000ff; font-family:微软雅黑; font-size:small\">[summon apc ]</span></p>\n\n<p><span style=\"color:#0000ff; font-family:微软雅黑; font-size:small\">15408 35 35 900000 1 </span></p>\n\n<p>&nbsp;</p>\n\n<p><span style=\"color:#0000ff; font-family:微软雅黑; font-size:small\">召唤APC：summon apc </span></p>\n\n<p><span style=\"color:#0000ff; font-family:微软雅黑; font-size:small\">第一个数值：APC编号</span></p>\n\n<p><span style=\"color:#0000ff; font-family:微软雅黑; font-size:small\">第二个数值：等级，当数值为-1时，与召唤者Lv相同</span></p>\n\n<p><span style=\"color:#0000ff; font-family:微软雅黑; font-size:small\">第三个数值：等级，当数值为-1时，与召唤者Lv相同</span></p>\n\n<p><span style=\"color:#0000ff; font-family:微软雅黑; font-size:small\">第四个数值：存在时间</span></p>\n\n<p><span style=\"color:#0000ff; font-family:微软雅黑; font-size:small\">第五个数值：召唤只数</span></p>\n\n<p><span style=\"color:#0000ff; font-family:微软雅黑; font-size:small\">召唤怪物：monster summons </span></p>\n\n<p><span style=\"color:#0000ff; font-family:微软雅黑; font-size:small\">数值意义与APC相同</span></p>\n\n<p><span style=\"color:#0000ff; font-family:微软雅黑; font-size:small\">召唤怪物会变身的几个编号</span></p>\n\n<p><span style=\"color:#0000ff; font-family:微软雅黑; font-size:small\">变身哥布林弓手：61735</span></p>\n\n<p><span style=\"color:#0000ff; font-family:微软雅黑; font-size:small\">变身幽灵赛莉亚：61736</span></p>\n\n<p><span style=\"color:#0000ff; font-family:微软雅黑; font-size:small\">变身机械牛：62132</span></p>\n\n<p><span style=\"color:#0000ff; font-family:微软雅黑; font-size:small\">变身蓝影马萨乔：62133</span></p>\n\n<p><span style=\"color:#0000ff; font-family:微软雅黑; font-size:small\">变身拉米：63008</span></p>\n\n<p><span style=\"color:#0000ff; font-family:微软雅黑; font-size:small\">变身多尼尔：63009</span></p>\n\n<p><span style=\"color:#0000ff; font-family:微软雅黑; font-size:small\">-------下面是未测试部分-----------</span></p>\n\n<p><span style=\"color:#0000ff; font-family:微软雅黑; font-size:small\">变身宾瑟斯：62143</span></p>\n\n<p><span style=\"color:#0000ff; font-family:微软雅黑; font-size:small\">变身硕徒斯：63499</span></p>\n\n<p><span style=\"color:#0000ff; font-family:微软雅黑; font-size:small\">变身希哲思：63500</span></p>\n\n<p><span style=\"color:#0000ff; font-family:微软雅黑; font-size:small\">变身司其沃：62142</span></p>\n\n<p><span style=\"color:#0000ff; font-family:微软雅黑; font-size:small\">变身司其沃：61294</span></p>\n\n<p><span style=\"color:#0000ff; font-family:微软雅黑; font-size:small\">变身AT-5T 步行者：61235</span></p>\n\n<p><span style=\"color:#0000ff; font-family:微软雅黑; font-size:small\">变身爆破弹 P-36：61772 </span></p>\n\n<p><span style=\"color:#0000ff; font-family:微软雅黑; font-size:small\">变身爆破弹 P-36：61776</span></p>\n\n<p><span style=\"color:#0000ff; font-family:微软雅黑; font-size:small\">变身爆破弹 P-36：61777</span></p>\n\n<p><span style=\"color:#0000ff; font-family:微软雅黑; font-size:small\">变身爆破弹 P-36：61779</span></p>\n\n<p><span style=\"color:#0000ff; font-family:微软雅黑; font-size:small\">变身加特林机枪炮塔：63011</span></p>\n\n<p><span style=\"color:#0000ff; font-family:微软雅黑; font-size:small\">变身蓝影马萨乔：61249</span></p>\n\n<p><span style=\"color:#0000ff; font-family:微软雅黑; font-size:small\">变身冰齿沙凡特：无编号有路径：</span></p>\n\n<p><span style=\"color:#0000ff; font-family:微软雅黑; font-size:small\">monster/newmonsters/riding/shavante/shavante.mob </span></p>",
    "auth_users": "学院搬运工",
    "img": "https://dafstatic.oss-cn-beijing.aliyuncs.com/static/title/level4.gif",
    "create_at": "2023-05-06T22:00:12.438",
    "view_num": 422
}